README.md
setup.py
pytest_flaptastic/__init__.py
pytest_flaptastic/helper.py
pytest_flaptastic/plugin.py
pytest_flaptastic.egg-info/PKG-INFO
pytest_flaptastic.egg-info/SOURCES.txt
pytest_flaptastic.egg-info/dependency_links.txt
pytest_flaptastic.egg-info/entry_points.txt
pytest_flaptastic.egg-info/requires.txt
pytest_flaptastic.egg-info/top_level.txt