Metadata-Version: 2.1
Name: pytest-flaptastic
Version: 0.0.25
Summary: Flaptastic py.test plugin
Home-page: https://github.com/FlaptasticApps/pytest-flaptastic
Author: Jonathan Block
Author-email: jon.block@flaptastic.com
License: UNKNOWN
Platform: UNKNOWN
Classifier: Framework :: Pytest
Classifier: License :: OSI Approved :: MIT License
Classifier: Operating System :: OS Independent
